aproc/__init__.py
aproc/_version.py
aproc/worker.py
aproc-0.0.1.dist-info/LICENSE
aproc-0.0.1.dist-info/METADATA
aproc-0.0.1.dist-info/WHEEL
aproc-0.0.1.dist-info/top_level.txt
aproc-0.0.1.dist-info/RECORD
