Metadata-Version: 2.1
Name: aproc
Version: 0.0.1
Summary: aproc - for asynchronous multiprocessing
Home-page: https://github.com/pyiron/aproc
Author: Jan Janssen
Author-email: janssen@mpie.de
License: BSD
Keywords: aproc
Platform: UNKNOWN
Classifier: Development Status :: 5 - Production/Stable
Classifier: Topic :: Scientific/Engineering :: Physics
Classifier: License :: OSI Approved :: BSD License
Classifier: Intended Audience :: Science/Research
Classifier: Operating System :: OS Independent
Classifier: Programming Language :: Python :: 3.6
Classifier: Programming Language :: Python :: 3.7
Classifier: Programming Language :: Python :: 3.8
Classifier: Programming Language :: Python :: 3.9
License-File: LICENSE
